{"id":4,"receita":"Quiche de Espinafre com Queijo","ingredientes":"1 massa pronta para quiche, 200g de espinafre fresco, 1 xícara de queijo parmesão ralado, 1 xícara de queijo muçarela ralado, 3 ovos, 1 xícara de creme de leite, sal e pimenta a gosto, 1 cebola picada, 2 dentes de alho picados","modo_preparo":"1. Preaqueça o forno a 180°C. 2. Em uma frigideira, refogue a cebola e o alho até ficarem dourados. Adicione o espinafre e refogue até murchar. 3. Em uma tigela, bata os ovos, o creme de leite, o sal e a pimenta. 4. Adicione os queijos e o espinafre refogado à mistura de ovos. 5. Coloque a massa para quiche em uma forma, despeje a mistura sobre a massa. 6. Leve ao forno por aproximadamente 30-35 minutos ou até o recheio estar firme e dourado.","link_imagem":"https://static.itdg.com.br/images/360-240/04f97152aa37bf92d0ae8766fc17ae16/339092-original.jpg","tipo":"salgado","created_at":"2024-08-11T22:03:38.360Z","IngredientesBase":[{"id":4,"nomesIngrediente":["massa para quiche","espinafre","queijo parmesão","queijo muçarela","ovos","creme de leite","sal","pimenta","cebola","alho"],"receita_id":4,"created_at":"2024-08-11T22:03:38.360Z"}]}
